cuebung_helper
