Metadata-Version: 1.1
Name: cuebung-helper
Version: 0.3.0
Summary: Helper function to test c code with pytest
Home-page: https://gitlab.com/cuebung/cuebung_helper_functions
Author: Sebastian Stigler
Author-email: sebastian@sebastian-stigler.de
License: mit
Platform: UNKNOWN
Classifier: Development Status :: 4 - Beta
Classifier: Programming Language :: Python
Classifier: Programming Language :: Python :: 3.4
